azaka_dump_parser/__init__.py
azaka_dump_parser/parser.py
azaka_dump_parser/tag.py
azaka_dump_parser/trait.py
azaka_dump_parser/vote.py
azaka_dump_parser-0.1.0.dist-info/LICENSE
azaka_dump_parser-0.1.0.dist-info/WHEEL
azaka_dump_parser-0.1.0.dist-info/METADATA
azaka_dump_parser-0.1.0.dist-info/RECORD
